wsp_matrix_butler/__init__.py
wsp_matrix_butler/_version.py
wsp_matrix_butler/api.py
wsp_matrix_butler/butler.py
wsp_matrix_butler-2.0.0.dist-info/LICENSE
wsp_matrix_butler-2.0.0.dist-info/METADATA
wsp_matrix_butler-2.0.0.dist-info/WHEEL
wsp_matrix_butler-2.0.0.dist-info/top_level.txt
wsp_matrix_butler-2.0.0.dist-info/RECORD
