Metadata-Version: 2.1
Name: wsp-matrix-butler
Version: 2.0.0
Summary: A SQLite-based mini-file system for organizing binary files for the Greater Golden Horseshoe Model
Author-email: Brian Cheung <brian.cheung@wsp.com>
Project-URL: Homepage, https://github.com/wsp-sag/wsp-matrix-butler
Project-URL: Issues, https://github.com/wsp-sag/wsp-matrix-butler/issues
Classifier: Development Status :: 5 - Production/Stable
Classifier: License :: OSI Approved :: MIT License
Classifier: Operating System :: OS Independent
Classifier: Programming Language :: Python :: 3
Requires-Python: >=3.7
License-File: LICENSE
Requires-Dist: pandas>=0.24
Requires-Dist: numpy>=1.21
